{
    "home": "Milwaukee Bucks",
    "away": "Golden State Warriors",
    "home_score": 109,
    "away_score": 102,
    "home_team": {
        "Ellis,Monta": {
            "mp": "38:28",
            "fg": "7",
            "fga": "20",
            "fg_pct": ".350",
            "fg3": "1",
            "fg3a": "5",
            "fg3_pct": ".200",
            "ft": "5",
            "fta": "6",
            "ft_pct": ".833",
            "orb": "0",
            "drb": "4",
            "trb": "4",
            "ast": "4",
            "stl": "2",
            "blk": "1",
            "tov": "4",
            "pf": "2",
            "pts": "20",
            "plus_minus": "+9",
            "ts_pct": ".442",
            "efg_pct": ".375",
            "fg3a_per_fga_pct": ".250",
            "fta_per_fga_pct": ".300",
            "orb_pct": "0.0",
            "drb_pct": "10.4",
            "trb_pct": "4.6",
            "ast_pct": "15.5",
            "stl_pct": "2.6",
            "blk_pct": "1.9",
            "tov_pct": "15.0",
            "usg_pct": "27.3",
            "off_rtg": "91",
            "def_rtg": "104"
        },
        "Jennings,Brandon": {
            "mp": "38:14",
            "fg": "6",
            "fga": "15",
            "fg_pct": ".400",
            "fg3": "5",
            "fg3a": "8",
            "fg3_pct": ".625",
            "ft": "3",
            "fta": "4",
            "ft_pct": ".750",
            "orb": "3",
            "drb": "3",
            "trb": "6",
            "ast": "7",
            "stl": "0",
            "blk": "0",
            "tov": "1",
            "pf": "2",
            "pts": "20",
            "plus_minus": "+1",
            "ts_pct": ".597",
            "efg_pct": ".567",
            "fg3a_per_fga_pct": ".533",
            "fta_per_fga_pct": ".267",
            "orb_pct": "6.3",
            "drb_pct": "7.8",
            "trb_pct": "7.0",
            "ast_pct": "26.3",
            "stl_pct": "0.0",
            "blk_pct": "0.0",
            "tov_pct": "5.6",
            "usg_pct": "18.3",
            "off_rtg": "141",
            "def_rtg": "113"
        },
        "Ilyasova,Ersan": {
            "mp": "34:31",
            "fg": "7",
            "fga": "17",
            "fg_pct": ".412",
            "fg3": "2",
            "fg3a": "6",
            "fg3_pct": ".333",
            "ft": "2",
            "fta": "2",
            "ft_pct": "1.000",
            "orb": "5",
            "drb": "7",
            "trb": "12",
            "ast": "3",
            "stl": "2",
            "blk": "0",
            "tov": "1",
            "pf": "2",
            "pts": "18",
            "plus_minus": "+4",
            "ts_pct": ".503",
            "efg_pct": ".471",
            "fg3a_per_fga_pct": ".353",
            "fta_per_fga_pct": ".118",
            "orb_pct": "11.6",
            "drb_pct": "20.3",
            "trb_pct": "15.5",
            "ast_pct": "13.3",
            "stl_pct": "2.8",
            "blk_pct": "0.0",
            "tov_pct": "5.3",
            "usg_pct": "21.6",
            "off_rtg": "121",
            "def_rtg": "101"
        },
        "Sanders,Larry": {
            "mp": "29:30",
            "fg": "7",
            "fga": "9",
            "fg_pct": ".778",
            "fg3": "0",
            "fg3a": "0",
            "fg3_pct": "",
            "ft": "2",
            "fta": "2",
            "ft_pct": "1.000",
            "orb": "5",
            "drb": "6",
            "trb": "11",
            "ast": "1",
            "stl": "0",
            "blk": "3",
            "tov": "1",
            "pf": "4",
            "pts": "16",
            "plus_minus": "0",
            "ts_pct": ".810",
            "efg_pct": ".778",
            "fg3a_per_fga_pct": ".000",
            "fta_per_fga_pct": ".222",
            "orb_pct": "13.6",
            "drb_pct": "20.3",
            "trb_pct": "16.6",
            "ast_pct": "5.5",
            "stl_pct": "0.0",
            "blk_pct": "7.5",
            "tov_pct": "9.2",
            "usg_pct": "14.5",
            "off_rtg": "158",
            "def_rtg": "102"
        },
        "Mbah a Moute,Luc": {
            "mp": "27:47",
            "fg": "3",
            "fga": "12",
            "fg_pct": ".250",
            "fg3": "0",
            "fg3a": "0",
            "fg3_pct": "",
            "ft": "2",
            "fta": "6",
            "ft_pct": ".333",
            "orb": "4",
            "drb": "5",
            "trb": "9",
            "ast": "2",
            "stl": "0",
            "blk": "0",
            "tov": "0",
            "pf": "1",
            "pts": "8",
            "plus_minus": "+1",
            "ts_pct": ".273",
            "efg_pct": ".250",
            "fg3a_per_fga_pct": ".000",
            "fta_per_fga_pct": ".500",
            "orb_pct": "11.5",
            "drb_pct": "18.0",
            "trb_pct": "14.4",
            "ast_pct": "9.6",
            "stl_pct": "0.0",
            "blk_pct": "0.0",
            "tov_pct": "0.0",
            "usg_pct": "20.8",
            "off_rtg": "85",
            "def_rtg": "109"
        },
        "Udrih,Beno": {
            "mp": "20:53",
            "fg": "4",
            "fga": "12",
            "fg_pct": ".333",
            "fg3": "2",
            "fg3a": "5",
            "fg3_pct": ".400",
            "ft": "0",
            "fta": "0",
            "ft_pct": "",
            "orb": "2",
            "drb": "2",
            "trb": "4",
            "ast": "5",
            "stl": "0",
            "blk": "0",
            "tov": "1",
            "pf": "1",
            "pts": "10",
            "plus_minus": "-4",
            "ts_pct": ".417",
            "efg_pct": ".417",
            "fg3a_per_fga_pct": ".417",
            "fta_per_fga_pct": ".000",
            "orb_pct": "7.7",
            "drb_pct": "9.6",
            "trb_pct": "8.5",
            "ast_pct": "36.1",
            "stl_pct": "0.0",
            "blk_pct": "0.0",
            "tov_pct": "7.7",
            "usg_pct": "24.5",
            "off_rtg": "109",
            "def_rtg": "112"
        },
        "Dalembert,Samuel": {
            "mp": "18:30",
            "fg": "2",
            "fga": "4",
            "fg_pct": ".500",
            "fg3": "0",
            "fg3a": "0",
            "fg3_pct": "",
            "ft": "0",
            "fta": "0",
            "ft_pct": "",
            "orb": "2",
            "drb": "4",
            "trb": "6",
            "ast": "0",
            "stl": "1",
            "blk": "2",
            "tov": "1",
            "pf": "2",
            "pts": "4",
            "plus_minus": "+7",
            "ts_pct": ".500",
            "efg_pct": ".500",
            "fg3a_per_fga_pct": ".000",
            "fta_per_fga_pct": ".000",
            "orb_pct": "8.6",
            "drb_pct": "21.6",
            "trb_pct": "14.4",
            "ast_pct": "0.0",
            "stl_pct": "2.7",
            "blk_pct": "8.0",
            "tov_pct": "20.0",
            "usg_pct": "10.7",
            "off_rtg": "96",
            "def_rtg": "95"
        },
        "Dunleavy,Mike": {
            "mp": "17:03",
            "fg": "4",
            "fga": "9",
            "fg_pct": ".444",
            "fg3": "3",
            "fg3a": "6",
            "fg3_pct": ".500",
            "ft": "0",
            "fta": "0",
            "ft_pct": "",
            "orb": "0",
            "drb": "3",
            "trb": "3",
            "ast": "1",
            "stl": "1",
            "blk": "0",
            "tov": "1",
            "pf": "1",
            "pts": "11",
            "plus_minus": "+8",
            "ts_pct": ".611",
            "efg_pct": ".611",
            "fg3a_per_fga_pct": ".667",
            "fta_per_fga_pct": ".000",
            "orb_pct": "0.0",
            "drb_pct": "17.6",
            "trb_pct": "7.8",
            "ast_pct": "9.5",
            "stl_pct": "2.9",
            "blk_pct": "0.0",
            "tov_pct": "10.0",
            "usg_pct": "23.1",
            "off_rtg": "117",
            "def_rtg": "102"
        },
        "Udoh,Ekpe": {
            "mp": "9:01",
            "fg": "0",
            "fga": "0",
            "fg_pct": "",
            "fg3": "0",
            "fg3a": "0",
            "fg3_pct": "",
            "ft": "0",
            "fta": "0",
            "ft_pct": "",
            "orb": "1",
            "drb": "1",
            "trb": "2",
            "ast": "1",
            "stl": "1",
            "blk": "1",
            "tov": "1",
            "pf": "0",
            "pts": "0",
            "plus_minus": "+6",
            "ts_pct": "",
            "efg_pct": "",
            "fg3a_per_fga_pct": "",
            "fta_per_fga_pct": "",
            "orb_pct": "8.9",
            "drb_pct": "11.1",
            "trb_pct": "9.9",
            "ast_pct": "13.0",
            "stl_pct": "5.4",
            "blk_pct": "8.2",
            "tov_pct": "100.0",
            "usg_pct": "4.4",
            "off_rtg": "68",
            "def_rtg": "92"
        },
        "Daniels,Marquis": {
            "mp": "6:03",
            "fg": "1",
            "fga": "3",
            "fg_pct": ".333",
            "fg3": "0",
            "fg3a": "0",
            "fg3_pct": "",
            "ft": "0",
            "fta": "0",
            "ft_pct": "",
            "orb": "0",
            "drb": "1",
            "trb": "1",
            "ast": "0",
            "stl": "0",
            "blk": "0",
            "tov": "1",
            "pf": "0",
            "pts": "2",
            "plus_minus": "+3",
            "ts_pct": ".333",
            "efg_pct": ".333",
            "fg3a_per_fga_pct": ".000",
            "fta_per_fga_pct": ".000",
            "orb_pct": "0.0",
            "drb_pct": "16.5",
            "trb_pct": "7.3",
            "ast_pct": "0.0",
            "stl_pct": "0.0",
            "blk_pct": "0.0",
            "tov_pct": "25.0",
            "usg_pct": "26.1",
            "off_rtg": "53",
            "def_rtg": "109"
        }
    },
    "away_team": {
        "Thompson,Klay": {
            "mp": "38:36",
            "fg": "8",
            "fga": "21",
            "fg_pct": ".381",
            "fg3": "3",
            "fg3a": "11",
            "fg3_pct": ".273",
            "ft": "0",
            "fta": "0",
            "ft_pct": "",
            "orb": "0",
            "drb": "3",
            "trb": "3",
            "ast": "1",
            "stl": "2",
            "blk": "0",
            "tov": "1",
            "pf": "3",
            "pts": "19",
            "plus_minus": "-3",
            "ts_pct": ".452",
            "efg_pct": ".452",
            "fg3a_per_fga_pct": ".524",
            "fta_per_fga_pct": ".000",
            "orb_pct": "0.0",
            "drb_pct": "6.2",
            "trb_pct": "3.5",
            "ast_pct": "4.3",
            "stl_pct": "2.5",
            "blk_pct": "0.0",
            "tov_pct": "4.5",
            "usg_pct": "24.2",
            "off_rtg": "90",
            "def_rtg": "114"
        },
        "Lee,David": {
            "mp": "37:56",
            "fg": "6",
            "fga": "18",
            "fg_pct": ".333",
            "fg3": "0",
            "fg3a": "0",
            "fg3_pct": "",
            "ft": "0",
            "fta": "0",
            "ft_pct": "",
            "orb": "2",
            "drb": "13",
            "trb": "15",
            "ast": "5",
            "stl": "1",
            "blk": "0",
            "tov": "2",
            "pf": "3",
            "pts": "12",
            "plus_minus": "-2",
            "ts_pct": ".333",
            "efg_pct": ".333",
            "fg3a_per_fga_pct": ".000",
            "fta_per_fga_pct": ".000",
            "orb_pct": "5.3",
            "drb_pct": "27.4",
            "trb_pct": "17.6",
            "ast_pct": "20.1",
            "stl_pct": "1.3",
            "blk_pct": "0.0",
            "tov_pct": "10.0",
            "usg_pct": "22.4",
            "off_rtg": "81",
            "def_rtg": "103"
        },
        "Curry,Stephen": {
            "mp": "36:50",
            "fg": "8",
            "fga": "19",
            "fg_pct": ".421",
            "fg3": "5",
            "fg3a": "9",
            "fg3_pct": ".556",
            "ft": "5",
            "fta": "5",
            "ft_pct": "1.000",
            "orb": "2",
            "drb": "0",
            "trb": "2",
            "ast": "7",
            "stl": "1",
            "blk": "0",
            "tov": "2",
            "pf": "2",
            "pts": "26",
            "plus_minus": "-8",
            "ts_pct": ".613",
            "efg_pct": ".553",
            "fg3a_per_fga_pct": ".474",
            "fta_per_fga_pct": ".263",
            "orb_pct": "5.4",
            "drb_pct": "0.0",
            "trb_pct": "2.4",
            "ast_pct": "31.9",
            "stl_pct": "1.3",
            "blk_pct": "0.0",
            "tov_pct": "8.6",
            "usg_pct": "26.8",
            "off_rtg": "128",
            "def_rtg": "121"
        },
        "Barnes,Harrison": {
            "mp": "13:18",
            "fg": "2",
            "fga": "3",
            "fg_pct": ".667",
            "fg3": "1",
            "fg3a": "2",
            "fg3_pct": ".500",
            "ft": "2",
            "fta": "2",
            "ft_pct": "1.000",
            "orb": "0",
            "drb": "1",
            "trb": "1",
            "ast": "0",
            "stl": "1",
            "blk": "0",
            "tov": "2",
            "pf": "2",
            "pts": "7",
            "plus_minus": "-3",
            "ts_pct": ".902",
            "efg_pct": ".833",
            "fg3a_per_fga_pct": ".667",
            "fta_per_fga_pct": ".667",
            "orb_pct": "0.0",
            "drb_pct": "6.0",
            "trb_pct": "3.3",
            "ast_pct": "0.0",
            "stl_pct": "3.7",
            "blk_pct": "0.0",
            "tov_pct": "34.0",
            "usg_pct": "18.8",
            "off_rtg": "106",
            "def_rtg": "111"
        },
        "Ezeli,Festus": {
            "mp": "10:32",
            "fg": "0",
            "fga": "2",
            "fg_pct": ".000",
            "fg3": "0",
            "fg3a": "0",
            "fg3_pct": "",
            "ft": "0",
            "fta": "0",
            "ft_pct": "",
            "orb": "1",
            "drb": "1",
            "trb": "2",
            "ast": "0",
            "stl": "0",
            "blk": "0",
            "tov": "3",
            "pf": "1",
            "pts": "0",
            "plus_minus": "-9",
            "ts_pct": ".000",
            "efg_pct": ".000",
            "fg3a_per_fga_pct": ".000",
            "fta_per_fga_pct": ".000",
            "orb_pct": "9.5",
            "drb_pct": "7.6",
            "trb_pct": "8.4",
            "ast_pct": "0.0",
            "stl_pct": "0.0",
            "blk_pct": "0.0",
            "tov_pct": "60.0",
            "usg_pct": "20.2",
            "off_rtg": "13",
            "def_rtg": "119"
        },
        "Jack,Jarrett": {
            "mp": "34:32",
            "fg": "5",
            "fga": "12",
            "fg_pct": ".417",
            "fg3": "3",
            "fg3a": "3",
            "fg3_pct": "1.000",
            "ft": "0",
            "fta": "0",
            "ft_pct": "",
            "orb": "1",
            "drb": "2",
            "trb": "3",
            "ast": "10",
            "stl": "1",
            "blk": "1",
            "tov": "1",
            "pf": "3",
            "pts": "13",
            "plus_minus": "-4",
            "ts_pct": ".542",
            "efg_pct": ".542",
            "fg3a_per_fga_pct": ".250",
            "fta_per_fga_pct": ".000",
            "orb_pct": "2.9",
            "drb_pct": "4.6",
            "trb_pct": "3.9",
            "ast_pct": "43.4",
            "stl_pct": "1.4",
            "blk_pct": "2.0",
            "tov_pct": "7.7",
            "usg_pct": "16.0",
            "off_rtg": "129",
            "def_rtg": "117"
        },
        "Landry,Carl": {
            "mp": "31:23",
            "fg": "5",
            "fga": "9",
            "fg_pct": ".556",
            "fg3": "0",
            "fg3a": "0",
            "fg3_pct": "",
            "ft": "3",
            "fta": "3",
            "ft_pct": "1.000",
            "orb": "4",
            "drb": "10",
            "trb": "14",
            "ast": "1",
            "stl": "0",
            "blk": "0",
            "tov": "2",
            "pf": "5",
            "pts": "13",
            "plus_minus": "+8",
            "ts_pct": ".630",
            "efg_pct": ".556",
            "fg3a_per_fga_pct": ".000",
            "fta_per_fga_pct": ".333",
            "orb_pct": "12.7",
            "drb_pct": "25.5",
            "trb_pct": "19.8",
            "ast_pct": "4.9",
            "stl_pct": "0.0",
            "blk_pct": "0.0",
            "tov_pct": "16.2",
            "usg_pct": "16.7",
            "off_rtg": "119",
            "def_rtg": "107"
        },
        "Biedrins,Andris": {
            "mp": "13:48",
            "fg": "0",
            "fga": "0",
            "fg_pct": "",
            "fg3": "0",
            "fg3a": "0",
            "fg3_pct": "",
            "ft": "0",
            "fta": "0",
            "ft_pct": "",
            "orb": "2",
            "drb": "4",
            "trb": "6",
            "ast": "0",
            "stl": "0",
            "blk": "3",
            "tov": "0",
            "pf": "2",
            "pts": "0",
            "plus_minus": "-4",
            "ts_pct": "",
            "efg_pct": "",
            "fg3a_per_fga_pct": "",
            "fta_per_fga_pct": "",
            "orb_pct": "14.5",
            "drb_pct": "23.2",
            "trb_pct": "19.3",
            "ast_pct": "0.0",
            "stl_pct": "0.0",
            "blk_pct": "14.7",
            "tov_pct": "",
            "usg_pct": "0.0",
            "off_rtg": "235",
            "def_rtg": "101"
        },
        "Jefferson,Richard": {
            "mp": "12:37",
            "fg": "4",
            "fga": "6",
            "fg_pct": ".667",
            "fg3": "1",
            "fg3a": "2",
            "fg3_pct": ".500",
            "ft": "0",
            "fta": "0",
            "ft_pct": "",
            "orb": "0",
            "drb": "2",
            "trb": "2",
            "ast": "1",
            "stl": "1",
            "blk": "0",
            "tov": "1",
            "pf": "2",
            "pts": "9",
            "plus_minus": "0",
            "ts_pct": ".750",
            "efg_pct": ".750",
            "fg3a_per_fga_pct": ".333",
            "fta_per_fga_pct": ".000",
            "orb_pct": "0.0",
            "drb_pct": "12.7",
            "trb_pct": "7.0",
            "ast_pct": "16.0",
            "stl_pct": "3.9",
            "blk_pct": "0.0",
            "tov_pct": "14.3",
            "usg_pct": "23.6",
            "off_rtg": "119",
            "def_rtg": "107"
        },
        "Green,Draymond": {
            "mp": "10:09",
            "fg": "1",
            "fga": "3",
            "fg_pct": ".333",
            "fg3": "0",
            "fg3a": "1",
            "fg3_pct": ".000",
            "ft": "1",
            "fta": "1",
            "ft_pct": "1.000",
            "orb": "0",
            "drb": "1",
            "trb": "1",
            "ast": "0",
            "stl": "1",
            "blk": "0",
            "tov": "1",
            "pf": "2",
            "pts": "3",
            "plus_minus": "-10",
            "ts_pct": ".436",
            "efg_pct": ".333",
            "fg3a_per_fga_pct": ".333",
            "fta_per_fga_pct": ".333",
            "orb_pct": "0.0",
            "drb_pct": "7.9",
            "trb_pct": "4.4",
            "ast_pct": "0.0",
            "stl_pct": "4.8",
            "blk_pct": "0.0",
            "tov_pct": "22.5",
            "usg_pct": "18.6",
            "off_rtg": "70",
            "def_rtg": "107"
        },
        "Bazemore,Kent": {
            "mp": "0:10",
            "fg": "0",
            "fga": "0",
            "fg_pct": "",
            "fg3": "0",
            "fg3a": "0",
            "fg3_pct": "",
            "ft": "0",
            "fta": "0",
            "ft_pct": "",
            "orb": "0",
            "drb": "1",
            "trb": "1",
            "ast": "0",
            "stl": "0",
            "blk": "0",
            "tov": "0",
            "pf": "0",
            "pts": "0",
            "plus_minus": "0",
            "ts_pct": "",
            "efg_pct": "",
            "fg3a_per_fga_pct": "",
            "fta_per_fga_pct": "",
            "orb_pct": "0.0",
            "drb_pct": "100.0",
            "trb_pct": "100.0",
            "ast_pct": "0.0",
            "stl_pct": "0.0",
            "blk_pct": "0.0",
            "tov_pct": "",
            "usg_pct": "0.0",
            "off_rtg": "0",
            "def_rtg": "-182"
        },
        "Jenkins,Charles": {
            "mp": "0:10",
            "fg": "0",
            "fga": "0",
            "fg_pct": "",
            "fg3": "0",
            "fg3a": "0",
            "fg3_pct": "",
            "ft": "0",
            "fta": "0",
            "ft_pct": "",
            "orb": "0",
            "drb": "0",
            "trb": "0",
            "ast": "0",
            "stl": "0",
            "blk": "0",
            "tov": "0",
            "pf": "0",
            "pts": "0",
            "plus_minus": "0",
            "ts_pct": "",
            "efg_pct": "",
            "fg3a_per_fga_pct": "",
            "fta_per_fga_pct": "",
            "orb_pct": "0.0",
            "drb_pct": "0.0",
            "trb_pct": "0.0",
            "ast_pct": "0.0",
            "stl_pct": "0.0",
            "blk_pct": "0.0",
            "tov_pct": "",
            "usg_pct": "0.0",
            "off_rtg": "0",
            "def_rtg": "124"
        }
    },
    "home_shooting": {
        "fg": 41,
        "fga": 101,
        "fg2": 28,
        "fg2a": 71,
        "fg3": 13,
        "fg3a": 30,
        "fg_ast": 24,
        "fg_pct": 0.40594059405940597,
        "fg2_pct": 0.39436619718309857,
        "fg3_pct": 0.43333333333333335,
        "fg_ast_pct": 0.5853658536585366,
        "efg_pct": 0.47029702970297027
    },
    "away_shooting": {
        "fg": 39,
        "fga": 93,
        "fg2": 26,
        "fg2a": 65,
        "fg3": 13,
        "fg3a": 28,
        "fg_ast": 25,
        "fg_pct": 0.41935483870967744,
        "fg2_pct": 0.4,
        "fg3_pct": 0.4642857142857143,
        "fg_ast_pct": 0.6410256410256411,
        "efg_pct": 0.489247311827957
    }
}