{
    "home": "Portland Trail Blazers",
    "away": "Oklahoma City Thunder",
    "home_score": 83,
    "away_score": 87,
    "home_team": {
        "Batum,Nicolas": {
            "mp": "43:53",
            "fg": "6",
            "fga": "17",
            "fg_pct": ".353",
            "fg3": "3",
            "fg3a": "8",
            "fg3_pct": ".375",
            "ft": "6",
            "fta": "6",
            "ft_pct": "1.000",
            "orb": "2",
            "drb": "5",
            "trb": "7",
            "ast": "2",
            "stl": "1",
            "blk": "1",
            "tov": "3",
            "pf": "4",
            "pts": "21",
            "plus_minus": "-7",
            "ts_pct": ".535",
            "efg_pct": ".441",
            "fg3a_per_fga_pct": ".471",
            "fta_per_fga_pct": ".353",
            "orb_pct": "4.5",
            "drb_pct": "15.2",
            "trb_pct": "9.0",
            "ast_pct": "9.0",
            "stl_pct": "1.2",
            "blk_pct": "2.3",
            "tov_pct": "13.3",
            "usg_pct": "23.4",
            "off_rtg": "103",
            "def_rtg": "97"
        },
        "Lillard,Damian": {
            "mp": "40:50",
            "fg": "3",
            "fga": "14",
            "fg_pct": ".214",
            "fg3": "2",
            "fg3a": "9",
            "fg3_pct": ".222",
            "ft": "1",
            "fta": "2",
            "ft_pct": ".500",
            "orb": "1",
            "drb": "3",
            "trb": "4",
            "ast": "9",
            "stl": "1",
            "blk": "0",
            "tov": "3",
            "pf": "2",
            "pts": "9",
            "plus_minus": "-2",
            "ts_pct": ".302",
            "efg_pct": ".286",
            "fg3a_per_fga_pct": ".643",
            "fta_per_fga_pct": ".143",
            "orb_pct": "2.4",
            "drb_pct": "9.8",
            "trb_pct": "5.5",
            "ast_pct": "38.5",
            "stl_pct": "1.3",
            "blk_pct": "0.0",
            "tov_pct": "16.8",
            "usg_pct": "19.8",
            "off_rtg": "74",
            "def_rtg": "100"
        },
        "Matthews,Wesley": {
            "mp": "39:12",
            "fg": "2",
            "fga": "8",
            "fg_pct": ".250",
            "fg3": "1",
            "fg3a": "2",
            "fg3_pct": ".500",
            "ft": "2",
            "fta": "2",
            "ft_pct": "1.000",
            "orb": "1",
            "drb": "0",
            "trb": "1",
            "ast": "4",
            "stl": "1",
            "blk": "1",
            "tov": "2",
            "pf": "4",
            "pts": "7",
            "plus_minus": "-1",
            "ts_pct": ".394",
            "efg_pct": ".313",
            "fg3a_per_fga_pct": ".250",
            "fta_per_fga_pct": ".250",
            "orb_pct": "2.5",
            "drb_pct": "0.0",
            "trb_pct": "1.4",
            "ast_pct": "17.2",
            "stl_pct": "1.4",
            "blk_pct": "2.6",
            "tov_pct": "18.4",
            "usg_pct": "12.6",
            "off_rtg": "84",
            "def_rtg": "99"
        },
        "Aldridge,LaMarcus": {
            "mp": "38:08",
            "fg": "15",
            "fga": "26",
            "fg_pct": ".577",
            "fg3": "0",
            "fg3a": "0",
            "fg3_pct": "",
            "ft": "3",
            "fta": "3",
            "ft_pct": "1.000",
            "orb": "2",
            "drb": "9",
            "trb": "11",
            "ast": "0",
            "stl": "0",
            "blk": "2",
            "tov": "2",
            "pf": "2",
            "pts": "33",
            "plus_minus": "0",
            "ts_pct": ".604",
            "efg_pct": ".577",
            "fg3a_per_fga_pct": ".000",
            "fta_per_fga_pct": ".115",
            "orb_pct": "5.1",
            "drb_pct": "31.5",
            "trb_pct": "16.3",
            "ast_pct": "0.0",
            "stl_pct": "0.0",
            "blk_pct": "5.2",
            "tov_pct": "6.8",
            "usg_pct": "34.8",
            "off_rtg": "114",
            "def_rtg": "95"
        },
        "Hickson,J.J.": {
            "mp": "25:35",
            "fg": "2",
            "fga": "7",
            "fg_pct": ".286",
            "fg3": "0",
            "fg3a": "0",
            "fg3_pct": "",
            "ft": "3",
            "fta": "5",
            "ft_pct": ".600",
            "orb": "1",
            "drb": "8",
            "trb": "9",
            "ast": "1",
            "stl": "0",
            "blk": "1",
            "tov": "1",
            "pf": "2",
            "pts": "7",
            "plus_minus": "-10",
            "ts_pct": ".380",
            "efg_pct": ".286",
            "fg3a_per_fga_pct": ".000",
            "fta_per_fga_pct": ".714",
            "orb_pct": "3.8",
            "drb_pct": "41.7",
            "trb_pct": "19.9",
            "ast_pct": "6.9",
            "stl_pct": "0.0",
            "blk_pct": "3.9",
            "tov_pct": "9.8",
            "usg_pct": "18.1",
            "off_rtg": "82",
            "def_rtg": "94"
        },
        "Pavlovic,Sasha": {
            "mp": "13:49",
            "fg": "0",
            "fga": "1",
            "fg_pct": ".000",
            "fg3": "0",
            "fg3a": "0",
            "fg3_pct": "",
            "ft": "0",
            "fta": "0",
            "ft_pct": "",
            "orb": "0",
            "drb": "1",
            "trb": "1",
            "ast": "0",
            "stl": "0",
            "blk": "0",
            "tov": "0",
            "pf": "0",
            "pts": "0",
            "plus_minus": "+3",
            "ts_pct": ".000",
            "efg_pct": ".000",
            "fg3a_per_fga_pct": ".000",
            "fta_per_fga_pct": ".000",
            "orb_pct": "0.0",
            "drb_pct": "9.7",
            "trb_pct": "4.1",
            "ast_pct": "0.0",
            "stl_pct": "0.0",
            "blk_pct": "0.0",
            "tov_pct": "0.0",
            "usg_pct": "3.3",
            "off_rtg": "0",
            "def_rtg": "103"
        },
        "Barton,Will": {
            "mp": "8:55",
            "fg": "1",
            "fga": "3",
            "fg_pct": ".333",
            "fg3": "0",
            "fg3a": "0",
            "fg3_pct": "",
            "ft": "0",
            "fta": "0",
            "ft_pct": "",
            "orb": "0",
            "drb": "1",
            "trb": "1",
            "ast": "0",
            "stl": "0",
            "blk": "1",
            "tov": "0",
            "pf": "1",
            "pts": "2",
            "plus_minus": "+2",
            "ts_pct": ".333",
            "efg_pct": ".333",
            "fg3a_per_fga_pct": ".000",
            "fta_per_fga_pct": ".000",
            "orb_pct": "0.0",
            "drb_pct": "15.0",
            "trb_pct": "6.3",
            "ast_pct": "0.0",
            "stl_pct": "0.0",
            "blk_pct": "11.2",
            "tov_pct": "0.0",
            "usg_pct": "15.2",
            "off_rtg": "72",
            "def_rtg": "93"
        },
        "Freeland,Joel": {
            "mp": "8:48",
            "fg": "0",
            "fga": "1",
            "fg_pct": ".000",
            "fg3": "0",
            "fg3a": "0",
            "fg3_pct": "",
            "ft": "0",
            "fta": "0",
            "ft_pct": "",
            "orb": "1",
            "drb": "2",
            "trb": "3",
            "ast": "0",
            "stl": "0",
            "blk": "0",
            "tov": "0",
            "pf": "1",
            "pts": "0",
            "plus_minus": "+3",
            "ts_pct": ".000",
            "efg_pct": ".000",
            "fg3a_per_fga_pct": ".000",
            "fta_per_fga_pct": ".000",
            "orb_pct": "11.1",
            "drb_pct": "30.3",
            "trb_pct": "19.3",
            "ast_pct": "0.0",
            "stl_pct": "0.0",
            "blk_pct": "0.0",
            "tov_pct": "0.0",
            "usg_pct": "5.1",
            "off_rtg": "52",
            "def_rtg": "99"
        },
        "Price,Ronnie": {
            "mp": "7:10",
            "fg": "1",
            "fga": "4",
            "fg_pct": ".250",
            "fg3": "0",
            "fg3a": "0",
            "fg3_pct": "",
            "ft": "0",
            "fta": "0",
            "ft_pct": "",
            "orb": "1",
            "drb": "0",
            "trb": "1",
            "ast": "0",
            "stl": "0",
            "blk": "0",
            "tov": "0",
            "pf": "2",
            "pts": "2",
            "plus_minus": "-2",
            "ts_pct": ".250",
            "efg_pct": ".250",
            "fg3a_per_fga_pct": ".000",
            "fta_per_fga_pct": ".000",
            "orb_pct": "13.7",
            "drb_pct": "0.0",
            "trb_pct": "7.9",
            "ast_pct": "0.0",
            "stl_pct": "0.0",
            "blk_pct": "0.0",
            "tov_pct": "0.0",
            "usg_pct": "25.3",
            "off_rtg": "67",
            "def_rtg": "104"
        },
        "Babbitt,Luke": {
            "mp": "6:59",
            "fg": "0",
            "fga": "3",
            "fg_pct": ".000",
            "fg3": "0",
            "fg3a": "2",
            "fg3_pct": ".000",
            "ft": "0",
            "fta": "0",
            "ft_pct": "",
            "orb": "1",
            "drb": "0",
            "trb": "1",
            "ast": "1",
            "stl": "0",
            "blk": "0",
            "tov": "1",
            "pf": "0",
            "pts": "0",
            "plus_minus": "-4",
            "ts_pct": ".000",
            "efg_pct": ".000",
            "fg3a_per_fga_pct": ".667",
            "fta_per_fga_pct": ".000",
            "orb_pct": "14.0",
            "drb_pct": "0.0",
            "trb_pct": "8.1",
            "ast_pct": "22.2",
            "stl_pct": "0.0",
            "blk_pct": "0.0",
            "tov_pct": "25.0",
            "usg_pct": "26.0",
            "off_rtg": "25",
            "def_rtg": "104"
        },
        "Jeffries,Jared": {
            "mp": "6:41",
            "fg": "1",
            "fga": "2",
            "fg_pct": ".500",
            "fg3": "0",
            "fg3a": "0",
            "fg3_pct": "",
            "ft": "0",
            "fta": "0",
            "ft_pct": "",
            "orb": "2",
            "drb": "1",
            "trb": "3",
            "ast": "0",
            "stl": "0",
            "blk": "0",
            "tov": "0",
            "pf": "0",
            "pts": "2",
            "plus_minus": "-2",
            "ts_pct": ".500",
            "efg_pct": ".500",
            "fg3a_per_fga_pct": ".000",
            "fta_per_fga_pct": ".000",
            "orb_pct": "29.3",
            "drb_pct": "20.0",
            "trb_pct": "25.3",
            "ast_pct": "0.0",
            "stl_pct": "0.0",
            "blk_pct": "0.0",
            "tov_pct": "0.0",
            "usg_pct": "13.6",
            "off_rtg": "129",
            "def_rtg": "101"
        }
    },
    "away_team": {
        "Liggins,DeAndre": {
            "mp": "39:36",
            "fg": "4",
            "fga": "6",
            "fg_pct": ".667",
            "fg3": "3",
            "fg3a": "3",
            "fg3_pct": "1.000",
            "ft": "0",
            "fta": "0",
            "ft_pct": "",
            "orb": "0",
            "drb": "9",
            "trb": "9",
            "ast": "2",
            "stl": "1",
            "blk": "0",
            "tov": "3",
            "pf": "4",
            "pts": "11",
            "plus_minus": "+8",
            "ts_pct": ".917",
            "efg_pct": ".917",
            "fg3a_per_fga_pct": ".500",
            "fta_per_fga_pct": ".000",
            "orb_pct": "0.0",
            "drb_pct": "22.3",
            "trb_pct": "12.8",
            "ast_pct": "8.9",
            "stl_pct": "1.4",
            "blk_pct": "0.0",
            "tov_pct": "33.3",
            "usg_pct": "11.4",
            "off_rtg": "107",
            "def_rtg": "91"
        },
        "Durant,Kevin": {
            "mp": "39:13",
            "fg": "12",
            "fga": "21",
            "fg_pct": ".571",
            "fg3": "2",
            "fg3a": "9",
            "fg3_pct": ".222",
            "ft": "7",
            "fta": "8",
            "ft_pct": ".875",
            "orb": "1",
            "drb": "3",
            "trb": "4",
            "ast": "6",
            "stl": "0",
            "blk": "2",
            "tov": "3",
            "pf": "3",
            "pts": "33",
            "plus_minus": "+7",
            "ts_pct": ".673",
            "efg_pct": ".619",
            "fg3a_per_fga_pct": ".429",
            "fta_per_fga_pct": ".381",
            "orb_pct": "3.4",
            "drb_pct": "7.5",
            "trb_pct": "5.8",
            "ast_pct": "42.4",
            "stl_pct": "0.0",
            "blk_pct": "3.8",
            "tov_pct": "10.9",
            "usg_pct": "35.2",
            "off_rtg": "125",
            "def_rtg": "97"
        },
        "Westbrook,Russell": {
            "mp": "34:09",
            "fg": "5",
            "fga": "21",
            "fg_pct": ".238",
            "fg3": "1",
            "fg3a": "5",
            "fg3_pct": ".200",
            "ft": "7",
            "fta": "9",
            "ft_pct": ".778",
            "orb": "2",
            "drb": "6",
            "trb": "8",
            "ast": "9",
            "stl": "0",
            "blk": "0",
            "tov": "3",
            "pf": "1",
            "pts": "18",
            "plus_minus": "+9",
            "ts_pct": ".361",
            "efg_pct": ".262",
            "fg3a_per_fga_pct": ".238",
            "fta_per_fga_pct": ".429",
            "orb_pct": "7.8",
            "drb_pct": "17.2",
            "trb_pct": "13.2",
            "ast_pct": "50.7",
            "stl_pct": "0.0",
            "blk_pct": "0.0",
            "tov_pct": "10.7",
            "usg_pct": "41.1",
            "off_rtg": "86",
            "def_rtg": "96"
        },
        "Perkins,Kendrick": {
            "mp": "33:27",
            "fg": "1",
            "fga": "3",
            "fg_pct": ".333",
            "fg3": "0",
            "fg3a": "0",
            "fg3_pct": "",
            "ft": "1",
            "fta": "2",
            "ft_pct": ".500",
            "orb": "2",
            "drb": "10",
            "trb": "12",
            "ast": "0",
            "stl": "2",
            "blk": "0",
            "tov": "1",
            "pf": "3",
            "pts": "3",
            "plus_minus": "+5",
            "ts_pct": ".387",
            "efg_pct": ".333",
            "fg3a_per_fga_pct": ".000",
            "fta_per_fga_pct": ".667",
            "orb_pct": "8.0",
            "drb_pct": "29.3",
            "trb_pct": "20.3",
            "ast_pct": "0.0",
            "stl_pct": "3.2",
            "blk_pct": "0.0",
            "tov_pct": "20.5",
            "usg_pct": "7.3",
            "off_rtg": "83",
            "def_rtg": "84"
        },
        "Collison,Nick": {
            "mp": "21:31",
            "fg": "4",
            "fga": "5",
            "fg_pct": ".800",
            "fg3": "0",
            "fg3a": "0",
            "fg3_pct": "",
            "ft": "0",
            "fta": "0",
            "ft_pct": "",
            "orb": "0",
            "drb": "3",
            "trb": "3",
            "ast": "0",
            "stl": "0",
            "blk": "0",
            "tov": "0",
            "pf": "3",
            "pts": "8",
            "plus_minus": "+10",
            "ts_pct": ".800",
            "efg_pct": ".800",
            "fg3a_per_fga_pct": ".000",
            "fta_per_fga_pct": ".000",
            "orb_pct": "0.0",
            "drb_pct": "13.7",
            "trb_pct": "7.9",
            "ast_pct": "0.0",
            "stl_pct": "0.0",
            "blk_pct": "0.0",
            "tov_pct": "0.0",
            "usg_pct": "11.7",
            "off_rtg": "152",
            "def_rtg": "97"
        },
        "Martin,Kevin": {
            "mp": "33:29",
            "fg": "1",
            "fga": "8",
            "fg_pct": ".125",
            "fg3": "0",
            "fg3a": "5",
            "fg3_pct": ".000",
            "ft": "2",
            "fta": "3",
            "ft_pct": ".667",
            "orb": "1",
            "drb": "1",
            "trb": "2",
            "ast": "2",
            "stl": "1",
            "blk": "0",
            "tov": "2",
            "pf": "0",
            "pts": "4",
            "plus_minus": "-10",
            "ts_pct": ".215",
            "efg_pct": ".125",
            "fg3a_per_fga_pct": ".625",
            "fta_per_fga_pct": ".375",
            "orb_pct": "4.0",
            "drb_pct": "2.9",
            "trb_pct": "3.4",
            "ast_pct": "9.4",
            "stl_pct": "1.6",
            "blk_pct": "0.0",
            "tov_pct": "17.7",
            "usg_pct": "17.0",
            "off_rtg": "52",
            "def_rtg": "99"
        },
        "Thabeet,Hasheem": {
            "mp": "16:25",
            "fg": "1",
            "fga": "1",
            "fg_pct": "1.000",
            "fg3": "0",
            "fg3a": "0",
            "fg3_pct": "",
            "ft": "0",
            "fta": "0",
            "ft_pct": "",
            "orb": "0",
            "drb": "2",
            "trb": "2",
            "ast": "0",
            "stl": "2",
            "blk": "1",
            "tov": "1",
            "pf": "2",
            "pts": "2",
            "plus_minus": "-6",
            "ts_pct": "1.000",
            "efg_pct": "1.000",
            "fg3a_per_fga_pct": ".000",
            "fta_per_fga_pct": ".000",
            "orb_pct": "0.0",
            "drb_pct": "11.9",
            "trb_pct": "6.9",
            "ast_pct": "0.0",
            "stl_pct": "6.5",
            "blk_pct": "4.5",
            "tov_pct": "50.0",
            "usg_pct": "6.1",
            "off_rtg": "76",
            "def_rtg": "81"
        },
        "Jackson,Reggie": {
            "mp": "14:28",
            "fg": "3",
            "fga": "5",
            "fg_pct": ".600",
            "fg3": "0",
            "fg3a": "1",
            "fg3_pct": ".000",
            "ft": "0",
            "fta": "0",
            "ft_pct": "",
            "orb": "0",
            "drb": "2",
            "trb": "2",
            "ast": "1",
            "stl": "0",
            "blk": "0",
            "tov": "1",
            "pf": "0",
            "pts": "6",
            "plus_minus": "-3",
            "ts_pct": ".600",
            "efg_pct": ".600",
            "fg3a_per_fga_pct": ".200",
            "fta_per_fga_pct": ".000",
            "orb_pct": "0.0",
            "drb_pct": "13.5",
            "trb_pct": "7.8",
            "ast_pct": "15.1",
            "stl_pct": "0.0",
            "blk_pct": "0.0",
            "tov_pct": "16.7",
            "usg_pct": "20.8",
            "off_rtg": "97",
            "def_rtg": "98"
        },
        "Jones,Perry": {
            "mp": "7:42",
            "fg": "1",
            "fga": "1",
            "fg_pct": "1.000",
            "fg3": "0",
            "fg3a": "0",
            "fg3_pct": "",
            "ft": "0",
            "fta": "0",
            "ft_pct": "",
            "orb": "0",
            "drb": "1",
            "trb": "1",
            "ast": "0",
            "stl": "0",
            "blk": "0",
            "tov": "1",
            "pf": "3",
            "pts": "2",
            "plus_minus": "0",
            "ts_pct": "1.000",
            "efg_pct": "1.000",
            "fg3a_per_fga_pct": ".000",
            "fta_per_fga_pct": ".000",
            "orb_pct": "0.0",
            "drb_pct": "12.7",
            "trb_pct": "7.3",
            "ast_pct": "0.0",
            "stl_pct": "0.0",
            "blk_pct": "0.0",
            "tov_pct": "50.0",
            "usg_pct": "13.0",
            "off_rtg": "74",
            "def_rtg": "97"
        }
    },
    "home_shooting": {
        "fg": 31,
        "fga": 86,
        "fg2": 25,
        "fg2a": 65,
        "fg3": 6,
        "fg3a": 21,
        "fg_ast": 17,
        "fg_pct": 0.36046511627906974,
        "fg2_pct": 0.38461538461538464,
        "fg3_pct": 0.2857142857142857,
        "fg_ast_pct": 0.5483870967741935,
        "efg_pct": 0.3953488372093023
    },
    "away_shooting": {
        "fg": 32,
        "fga": 71,
        "fg2": 26,
        "fg2a": 48,
        "fg3": 6,
        "fg3a": 23,
        "fg_ast": 20,
        "fg_pct": 0.4507042253521127,
        "fg2_pct": 0.5416666666666666,
        "fg3_pct": 0.2608695652173913,
        "fg_ast_pct": 0.625,
        "efg_pct": 0.49295774647887325
    }
}