{
    "home": "Los Angeles Lakers",
    "away": "New Jersey Nets",
    "home_score": 91,
    "away_score": 87,
    "home_team": {
        "Gasol,Pau": {
            "mp": "41:13",
            "fg": "11",
            "fga": "20",
            "fg_pct": ".550",
            "fg3": "0",
            "fg3a": "0",
            "fg3_pct": "",
            "ft": "0",
            "fta": "0",
            "ft_pct": "",
            "orb": "4",
            "drb": "8",
            "trb": "12",
            "ast": "4",
            "stl": "1",
            "blk": "0",
            "tov": "2",
            "pf": "2",
            "pts": "22",
            "plus_minus": "+2",
            "ts_pct": ".550",
            "efg_pct": ".550",
            "fg3a_per_fga_pct": ".000",
            "fta_per_fga_pct": ".000",
            "orb_pct": "11.9",
            "drb_pct": "19.0",
            "trb_pct": "15.9",
            "ast_pct": "17.8",
            "stl_pct": "1.3",
            "blk_pct": "0.0",
            "tov_pct": "9.1",
            "usg_pct": "25.7",
            "off_rtg": "113",
            "def_rtg": "99"
        },
        "Sessions,Ramon": {
            "mp": "37:47",
            "fg": "7",
            "fga": "15",
            "fg_pct": ".467",
            "fg3": "0",
            "fg3a": "2",
            "fg3_pct": ".000",
            "ft": "5",
            "fta": "5",
            "ft_pct": "1.000",
            "orb": "2",
            "drb": "4",
            "trb": "6",
            "ast": "11",
            "stl": "1",
            "blk": "0",
            "tov": "4",
            "pf": "2",
            "pts": "19",
            "plus_minus": "+7",
            "ts_pct": ".552",
            "efg_pct": ".467",
            "fg3a_per_fga_pct": ".133",
            "fta_per_fga_pct": ".333",
            "orb_pct": "6.5",
            "drb_pct": "10.4",
            "trb_pct": "8.7",
            "ast_pct": "46.4",
            "stl_pct": "1.5",
            "blk_pct": "0.0",
            "tov_pct": "18.9",
            "usg_pct": "27.0",
            "off_rtg": "115",
            "def_rtg": "102"
        },
        "Bryant,Kobe": {
            "mp": "35:45",
            "fg": "10",
            "fga": "16",
            "fg_pct": ".625",
            "fg3": "3",
            "fg3a": "6",
            "fg3_pct": ".500",
            "ft": "1",
            "fta": "1",
            "ft_pct": "1.000",
            "orb": "0",
            "drb": "7",
            "trb": "7",
            "ast": "3",
            "stl": "1",
            "blk": "0",
            "tov": "3",
            "pf": "1",
            "pts": "24",
            "plus_minus": "+1",
            "ts_pct": ".730",
            "efg_pct": ".719",
            "fg3a_per_fga_pct": ".375",
            "fta_per_fga_pct": ".063",
            "orb_pct": "0.0",
            "drb_pct": "19.2",
            "trb_pct": "10.7",
            "ast_pct": "15.8",
            "stl_pct": "1.6",
            "blk_pct": "0.0",
            "tov_pct": "15.4",
            "usg_pct": "26.2",
            "off_rtg": "120",
            "def_rtg": "99"
        },
        "McRoberts,Josh": {
            "mp": "27:16",
            "fg": "2",
            "fga": "6",
            "fg_pct": ".333",
            "fg3": "0",
            "fg3a": "0",
            "fg3_pct": "",
            "ft": "0",
            "fta": "0",
            "ft_pct": "",
            "orb": "1",
            "drb": "4",
            "trb": "5",
            "ast": "1",
            "stl": "0",
            "blk": "0",
            "tov": "1",
            "pf": "0",
            "pts": "4",
            "plus_minus": "+10",
            "ts_pct": ".333",
            "efg_pct": ".333",
            "fg3a_per_fga_pct": ".000",
            "fta_per_fga_pct": ".000",
            "orb_pct": "4.5",
            "drb_pct": "14.4",
            "trb_pct": "10.0",
            "ast_pct": "5.0",
            "stl_pct": "0.0",
            "blk_pct": "0.0",
            "tov_pct": "14.3",
            "usg_pct": "12.4",
            "off_rtg": "74",
            "def_rtg": "104"
        },
        "World Peace,Metta": {
            "mp": "25:26",
            "fg": "3",
            "fga": "8",
            "fg_pct": ".375",
            "fg3": "2",
            "fg3a": "5",
            "fg3_pct": ".400",
            "ft": "0",
            "fta": "0",
            "ft_pct": "",
            "orb": "0",
            "drb": "5",
            "trb": "5",
            "ast": "1",
            "stl": "0",
            "blk": "0",
            "tov": "0",
            "pf": "6",
            "pts": "8",
            "plus_minus": "+1",
            "ts_pct": ".500",
            "efg_pct": ".500",
            "fg3a_per_fga_pct": ".625",
            "fta_per_fga_pct": ".000",
            "orb_pct": "0.0",
            "drb_pct": "19.3",
            "trb_pct": "10.7",
            "ast_pct": "5.7",
            "stl_pct": "0.0",
            "blk_pct": "0.0",
            "tov_pct": "0.0",
            "usg_pct": "15.2",
            "off_rtg": "109",
            "def_rtg": "102"
        },
        "Murphy,Troy": {
            "mp": "25:17",
            "fg": "2",
            "fga": "4",
            "fg_pct": ".500",
            "fg3": "0",
            "fg3a": "1",
            "fg3_pct": ".000",
            "ft": "0",
            "fta": "0",
            "ft_pct": "",
            "orb": "1",
            "drb": "4",
            "trb": "5",
            "ast": "1",
            "stl": "0",
            "blk": "1",
            "tov": "1",
            "pf": "2",
            "pts": "4",
            "plus_minus": "-2",
            "ts_pct": ".500",
            "efg_pct": ".500",
            "fg3a_per_fga_pct": ".250",
            "fta_per_fga_pct": ".000",
            "orb_pct": "4.9",
            "drb_pct": "15.5",
            "trb_pct": "10.8",
            "ast_pct": "5.4",
            "stl_pct": "0.0",
            "blk_pct": "2.8",
            "tov_pct": "20.0",
            "usg_pct": "9.5",
            "off_rtg": "94",
            "def_rtg": "101"
        },
        "Barnes,Matt": {
            "mp": "24:48",
            "fg": "2",
            "fga": "6",
            "fg_pct": ".333",
            "fg3": "0",
            "fg3a": "2",
            "fg3_pct": ".000",
            "ft": "0",
            "fta": "0",
            "ft_pct": "",
            "orb": "3",
            "drb": "7",
            "trb": "10",
            "ast": "3",
            "stl": "1",
            "blk": "0",
            "tov": "5",
            "pf": "2",
            "pts": "4",
            "plus_minus": "+1",
            "ts_pct": ".333",
            "efg_pct": ".333",
            "fg3a_per_fga_pct": ".333",
            "fta_per_fga_pct": ".000",
            "orb_pct": "14.9",
            "drb_pct": "27.6",
            "trb_pct": "22.0",
            "ast_pct": "16.5",
            "stl_pct": "2.2",
            "blk_pct": "0.0",
            "tov_pct": "45.5",
            "usg_pct": "21.4",
            "off_rtg": "61",
            "def_rtg": "94"
        },
        "Blake,Steve": {
            "mp": "22:29",
            "fg": "2",
            "fga": "6",
            "fg_pct": ".333",
            "fg3": "2",
            "fg3a": "6",
            "fg3_pct": ".333",
            "ft": "0",
            "fta": "0",
            "ft_pct": "",
            "orb": "0",
            "drb": "0",
            "trb": "0",
            "ast": "3",
            "stl": "0",
            "blk": "0",
            "tov": "0",
            "pf": "1",
            "pts": "6",
            "plus_minus": "0",
            "ts_pct": ".500",
            "efg_pct": ".500",
            "fg3a_per_fga_pct": "1.000",
            "fta_per_fga_pct": ".000",
            "orb_pct": "0.0",
            "drb_pct": "0.0",
            "trb_pct": "0.0",
            "ast_pct": "18.4",
            "stl_pct": "0.0",
            "blk_pct": "0.0",
            "tov_pct": "0.0",
            "usg_pct": "12.9",
            "off_rtg": "123",
            "def_rtg": "109"
        }
    },
    "away_team": {
        "Wallace,Gerald": {
            "mp": "42:17",
            "fg": "7",
            "fga": "13",
            "fg_pct": ".538",
            "fg3": "2",
            "fg3a": "2",
            "fg3_pct": "1.000",
            "ft": "3",
            "fta": "4",
            "ft_pct": ".750",
            "orb": "0",
            "drb": "3",
            "trb": "3",
            "ast": "5",
            "stl": "1",
            "blk": "0",
            "tov": "0",
            "pf": "2",
            "pts": "19",
            "plus_minus": "-4",
            "ts_pct": ".644",
            "efg_pct": ".615",
            "fg3a_per_fga_pct": ".154",
            "fta_per_fga_pct": ".308",
            "orb_pct": "0.0",
            "drb_pct": "8.7",
            "trb_pct": "3.9",
            "ast_pct": "21.8",
            "stl_pct": "1.3",
            "blk_pct": "0.0",
            "tov_pct": "0.0",
            "usg_pct": "17.2",
            "off_rtg": "136",
            "def_rtg": "109"
        },
        "Humphries,Kris": {
            "mp": "39:18",
            "fg": "8",
            "fga": "15",
            "fg_pct": ".533",
            "fg3": "0",
            "fg3a": "0",
            "fg3_pct": "",
            "ft": "2",
            "fta": "2",
            "ft_pct": "1.000",
            "orb": "7",
            "drb": "8",
            "trb": "15",
            "ast": "3",
            "stl": "2",
            "blk": "1",
            "tov": "1",
            "pf": "0",
            "pts": "18",
            "plus_minus": "0",
            "ts_pct": ".567",
            "efg_pct": ".533",
            "fg3a_per_fga_pct": ".000",
            "fta_per_fga_pct": ".133",
            "orb_pct": "17.4",
            "drb_pct": "25.1",
            "trb_pct": "20.8",
            "ast_pct": "15.1",
            "stl_pct": "2.8",
            "blk_pct": "2.1",
            "tov_pct": "5.9",
            "usg_pct": "21.1",
            "off_rtg": "124",
            "def_rtg": "100"
        },
        "Williams,Deron": {
            "mp": "32:15",
            "fg": "6",
            "fga": "15",
            "fg_pct": ".400",
            "fg3": "2",
            "fg3a": "4",
            "fg3_pct": ".500",
            "ft": "6",
            "fta": "7",
            "ft_pct": ".857",
            "orb": "0",
            "drb": "3",
            "trb": "3",
            "ast": "6",
            "stl": "1",
            "blk": "0",
            "tov": "1",
            "pf": "4",
            "pts": "20",
            "plus_minus": "-12",
            "ts_pct": ".553",
            "efg_pct": ".467",
            "fg3a_per_fga_pct": ".267",
            "fta_per_fga_pct": ".467",
            "orb_pct": "0.0",
            "drb_pct": "11.4",
            "trb_pct": "5.1",
            "ast_pct": "35.6",
            "stl_pct": "1.7",
            "blk_pct": "0.0",
            "tov_pct": "5.2",
            "usg_pct": "29.1",
            "off_rtg": "116",
            "def_rtg": "108"
        },
        "Petro,Johan": {
            "mp": "20:35",
            "fg": "0",
            "fga": "8",
            "fg_pct": ".000",
            "fg3": "0",
            "fg3a": "0",
            "fg3_pct": "",
            "ft": "0",
            "fta": "0",
            "ft_pct": "",
            "orb": "3",
            "drb": "3",
            "trb": "6",
            "ast": "1",
            "stl": "0",
            "blk": "0",
            "tov": "0",
            "pf": "0",
            "pts": "0",
            "plus_minus": "-8",
            "ts_pct": ".000",
            "efg_pct": ".000",
            "fg3a_per_fga_pct": ".000",
            "fta_per_fga_pct": ".000",
            "orb_pct": "14.3",
            "drb_pct": "17.9",
            "trb_pct": "15.9",
            "ast_pct": "6.9",
            "stl_pct": "0.0",
            "blk_pct": "0.0",
            "tov_pct": "0.0",
            "usg_pct": "19.1",
            "off_rtg": "33",
            "def_rtg": "110"
        },
        "Brooks,MarShon": {
            "mp": "15:38",
            "fg": "2",
            "fga": "6",
            "fg_pct": ".333",
            "fg3": "1",
            "fg3a": "2",
            "fg3_pct": ".500",
            "ft": "0",
            "fta": "0",
            "ft_pct": "",
            "orb": "0",
            "drb": "0",
            "trb": "0",
            "ast": "2",
            "stl": "0",
            "blk": "0",
            "tov": "0",
            "pf": "1",
            "pts": "5",
            "plus_minus": "-12",
            "ts_pct": ".417",
            "efg_pct": ".417",
            "fg3a_per_fga_pct": ".333",
            "fta_per_fga_pct": ".000",
            "orb_pct": "0.0",
            "drb_pct": "0.0",
            "trb_pct": "0.0",
            "ast_pct": "22.0",
            "stl_pct": "0.0",
            "blk_pct": "0.0",
            "tov_pct": "0.0",
            "usg_pct": "18.9",
            "off_rtg": "95",
            "def_rtg": "115"
        },
        "Morrow,Anthony": {
            "mp": "27:11",
            "fg": "4",
            "fga": "11",
            "fg_pct": ".364",
            "fg3": "0",
            "fg3a": "5",
            "fg3_pct": ".000",
            "ft": "0",
            "fta": "0",
            "ft_pct": "",
            "orb": "0",
            "drb": "0",
            "trb": "0",
            "ast": "2",
            "stl": "2",
            "blk": "0",
            "tov": "0",
            "pf": "1",
            "pts": "8",
            "plus_minus": "+9",
            "ts_pct": ".364",
            "efg_pct": ".364",
            "fg3a_per_fga_pct": ".455",
            "fta_per_fga_pct": ".000",
            "orb_pct": "0.0",
            "drb_pct": "0.0",
            "trb_pct": "0.0",
            "ast_pct": "13.1",
            "stl_pct": "4.1",
            "blk_pct": "0.0",
            "tov_pct": "0.0",
            "usg_pct": "19.9",
            "off_rtg": "81",
            "def_rtg": "106"
        },
        "Green,Gerald": {
            "mp": "27:09",
            "fg": "5",
            "fga": "11",
            "fg_pct": ".455",
            "fg3": "1",
            "fg3a": "3",
            "fg3_pct": ".333",
            "ft": "2",
            "fta": "2",
            "ft_pct": "1.000",
            "orb": "0",
            "drb": "6",
            "trb": "6",
            "ast": "1",
            "stl": "1",
            "blk": "1",
            "tov": "1",
            "pf": "1",
            "pts": "13",
            "plus_minus": "+6",
            "ts_pct": ".547",
            "efg_pct": ".500",
            "fg3a_per_fga_pct": ".273",
            "fta_per_fga_pct": ".182",
            "orb_pct": "0.0",
            "drb_pct": "27.2",
            "trb_pct": "12.1",
            "ast_pct": "7.0",
            "stl_pct": "2.0",
            "blk_pct": "3.0",
            "tov_pct": "7.8",
            "usg_pct": "23.3",
            "off_rtg": "101",
            "def_rtg": "100"
        },
        "Williams,Jordan": {
            "mp": "14:42",
            "fg": "1",
            "fga": "2",
            "fg_pct": ".500",
            "fg3": "0",
            "fg3a": "0",
            "fg3_pct": "",
            "ft": "0",
            "fta": "0",
            "ft_pct": "",
            "orb": "0",
            "drb": "3",
            "trb": "3",
            "ast": "0",
            "stl": "0",
            "blk": "2",
            "tov": "0",
            "pf": "0",
            "pts": "2",
            "plus_minus": "-6",
            "ts_pct": ".500",
            "efg_pct": ".500",
            "fg3a_per_fga_pct": ".000",
            "fta_per_fga_pct": ".000",
            "orb_pct": "0.0",
            "drb_pct": "25.1",
            "trb_pct": "11.1",
            "ast_pct": "0.0",
            "stl_pct": "0.0",
            "blk_pct": "11.1",
            "tov_pct": "0.0",
            "usg_pct": "6.7",
            "off_rtg": "98",
            "def_rtg": "99"
        },
        "Gaines,Sundiata": {
            "mp": "11:24",
            "fg": "1",
            "fga": "4",
            "fg_pct": ".250",
            "fg3": "0",
            "fg3a": "2",
            "fg3_pct": ".000",
            "ft": "0",
            "fta": "0",
            "ft_pct": "",
            "orb": "0",
            "drb": "2",
            "trb": "2",
            "ast": "3",
            "stl": "1",
            "blk": "0",
            "tov": "2",
            "pf": "2",
            "pts": "2",
            "plus_minus": "+2",
            "ts_pct": ".250",
            "efg_pct": ".250",
            "fg3a_per_fga_pct": ".500",
            "fta_per_fga_pct": ".000",
            "orb_pct": "0.0",
            "drb_pct": "21.6",
            "trb_pct": "9.6",
            "ast_pct": "42.4",
            "stl_pct": "4.9",
            "blk_pct": "0.0",
            "tov_pct": "33.3",
            "usg_pct": "25.9",
            "off_rtg": "53",
            "def_rtg": "98"
        },
        "Stevenson,DeShawn": {
            "mp": "9:33",
            "fg": "0",
            "fga": "0",
            "fg_pct": "",
            "fg3": "0",
            "fg3a": "0",
            "fg3_pct": "",
            "ft": "0",
            "fta": "0",
            "ft_pct": "",
            "orb": "0",
            "drb": "0",
            "trb": "0",
            "ast": "0",
            "stl": "0",
            "blk": "0",
            "tov": "1",
            "pf": "0",
            "pts": "0",
            "plus_minus": "+5",
            "ts_pct": "",
            "efg_pct": "",
            "fg3a_per_fga_pct": "",
            "fta_per_fga_pct": "",
            "orb_pct": "0.0",
            "drb_pct": "0.0",
            "trb_pct": "0.0",
            "ast_pct": "0.0",
            "stl_pct": "0.0",
            "blk_pct": "0.0",
            "tov_pct": "100.0",
            "usg_pct": "5.1",
            "off_rtg": "0",
            "def_rtg": "115"
        }
    },
    "home_shooting": {
        "fg": 39,
        "fga": 81,
        "fg2": 32,
        "fg2a": 59,
        "fg3": 7,
        "fg3a": 22,
        "fg_ast": 27,
        "fg_pct": 0.48148148148148145,
        "fg2_pct": 0.5423728813559322,
        "fg3_pct": 0.3181818181818182,
        "fg_ast_pct": 0.6923076923076923,
        "efg_pct": 0.5246913580246914
    },
    "away_shooting": {
        "fg": 34,
        "fga": 85,
        "fg2": 28,
        "fg2a": 67,
        "fg3": 6,
        "fg3a": 18,
        "fg_ast": 23,
        "fg_pct": 0.4,
        "fg2_pct": 0.417910447761194,
        "fg3_pct": 0.3333333333333333,
        "fg_ast_pct": 0.6764705882352942,
        "efg_pct": 0.43529411764705883
    }
}